<annotation>
	<folder>pictures</folder>
	<filename>default_gzclient_camera(1)-2020-02-10T00_39_07.508043.jpg</filename>
	<path>/home/peter/NewDisk/kaikeba_drone/pictures/default_gzclient_camera(1)-2020-02-10T00_39_07.508043.jpg</path>
	<source>
		<database>Unknown</database>
	</source>
	<size>
		<width>1011</width>
		<height>610</height>
		<depth>3</depth>
	</size>
	<segmented>0</segmented>
	<object>
		<name>human</name>
		<pose>Unspecified</pose>
		<truncated>0</truncated>
		<difficult>0</difficult>
		<bndbox>
			<xmin>186</xmin>
			<ymin>296</ymin>
			<xmax>217</xmax>
			<ymax>396</ymax>
		</bndbox>
	</object>
	<object>
		<name>street sign</name>
		<pose>Unspecified</pose>
		<truncated>0</truncated>
		<difficult>0</difficult>
		<bndbox>
			<xmin>139</xmin>
			<ymin>272</ymin>
			<xmax>173</xmax>
			<ymax>366</ymax>
		</bndbox>
	</object>
	<object>
		<name>street sign</name>
		<pose>Unspecified</pose>
		<truncated>0</truncated>
		<difficult>0</difficult>
		<bndbox>
			<xmin>311</xmin>
			<ymin>257</ymin>
			<xmax>327</xmax>
			<ymax>321</ymax>
		</bndbox>
	</object>
	<object>
		<name>fire hydrant</name>
		<pose>Unspecified</pose>
		<truncated>0</truncated>
		<difficult>0</difficult>
		<bndbox>
			<xmin>369</xmin>
			<ymin>325</ymin>
			<xmax>400</xmax>
			<ymax>365</ymax>
		</bndbox>
	</object>
	<object>
		<name>car</name>
		<pose>Unspecified</pose>
		<truncated>0</truncated>
		<difficult>0</difficult>
		<bndbox>
			<xmin>269</xmin>
			<ymin>204</ymin>
			<xmax>344</xmax>
			<ymax>263</ymax>
		</bndbox>
	</object>
	<object>
		<name>street light</name>
		<pose>Unspecified</pose>
		<truncated>0</truncated>
		<difficult>0</difficult>
		<bndbox>
			<xmin>693</xmin>
			<ymin>268</ymin>
			<xmax>875</xmax>
			<ymax>608</ymax>
		</bndbox>
	</object>
</annotation>
